jlabbase/__init__.py
jlabbase-0.2.0.dist-info/WHEEL
jlabbase-0.2.0.dist-info/METADATA
jlabbase-0.2.0.dist-info/RECORD
