Metadata-Version: 2.1
Name: jlabbase
Version: 0.2.0
Summary: This is a small package wit jupyterlab, numpy and pandas. This package serves as base for larger jupyterlab packages.
Author: yZg
Requires-Python: >=3.9,<4.0
Classifier: Programming Language :: Python :: 3
Classifier: Programming Language :: Python :: 3.10
Classifier: Programming Language :: Python :: 3.9
Requires-Dist: jupyterlab
Requires-Dist: numpy
Requires-Dist: pandas
